sphinx_autodoc_toolbox/__init__.py
sphinx_autodoc_toolbox/_version.py
sphinx_autodoc_toolbox/collapse.py
sphinx_autodoc_toolbox-0.0.2.dist-info/LICENSE
sphinx_autodoc_toolbox-0.0.2.dist-info/METADATA
sphinx_autodoc_toolbox-0.0.2.dist-info/WHEEL
sphinx_autodoc_toolbox-0.0.2.dist-info/entry_points.txt
sphinx_autodoc_toolbox-0.0.2.dist-info/top_level.txt
sphinx_autodoc_toolbox-0.0.2.dist-info/RECORD
