Metadata-Version: 2.1
Name: sphinx-autodoc-toolbox
Version: 0.0.2
Summary: Extensions for sphinx autodoc
Author-email: WANG Hailin <hailin.wang@connect.polyu.hk>
Project-URL: Homepage, https://github.com/haiiliin/sphinx-autodoc-toolbox/
Project-URL: Documentation, https://sphinx-autodoc-toolbox.readthedocs.io/
Classifier: Programming Language :: Python
Classifier: Programming Language :: Python :: 3
Classifier: Programming Language :: Python :: 3.7
Classifier: Programming Language :: Python :: 3.8
Classifier: Programming Language :: Python :: 3.9
Classifier: Programming Language :: Python :: 3.10
Classifier: Programming Language :: Python :: 3.11
Classifier: Programming Language :: Python :: Implementation :: PyPy
Classifier: License :: OSI Approved :: MIT License
Classifier: Operating System :: OS Independent
Requires-Python: >=3.7
License-File: LICENSE
Requires-Dist: sphinx
Requires-Dist: sphinx-togglebutton
